skill_sdk/__init__.py
skill_sdk/__main__.py
skill_sdk/__version__.py
skill_sdk/config.py
skill_sdk/i18n.py
skill_sdk/log.py
skill_sdk/requests.py
skill_sdk/routes.py
skill_sdk/skill.py
skill_sdk/cli/__init__.py
skill_sdk/cli/develop.py
skill_sdk/cli/init.py
skill_sdk/cli/run.py
skill_sdk/cli/translate.py
skill_sdk/cli/version.py
skill_sdk/cli/scaffold/Dockerfile
skill_sdk/cli/scaffold/README.md
skill_sdk/cli/scaffold/app.py
skill_sdk/cli/scaffold/requirements-dev.txt
skill_sdk/cli/scaffold/requirements.txt
skill_sdk/cli/scaffold/skill.conf
skill_sdk/cli/scaffold/impl/__init__.py
skill_sdk/cli/scaffold/impl/test_impl.py
skill_sdk/cli/scaffold/locale/de.po
skill_sdk/cli/scaffold/locale/en.po
skill_sdk/cli/scaffold/locale/fr.po
skill_sdk/cli/scaffold/scripts/develop
skill_sdk/cli/scaffold/scripts/run
skill_sdk/cli/scaffold/scripts/test
skill_sdk/cli/scaffold/scripts/version
skill_sdk/intents/__init__.py
skill_sdk/intents/entities.py
skill_sdk/intents/handlers.py
skill_sdk/intents/request.py
skill_sdk/middleware/__init__.py
skill_sdk/middleware/error.py
skill_sdk/middleware/log.py
skill_sdk/middleware/prometheus.py
skill_sdk/middleware/skillassessment.py
skill_sdk/middleware/tracing.py
skill_sdk/responses/__init__.py
skill_sdk/responses/card.py
skill_sdk/responses/command.py
skill_sdk/responses/error.py
skill_sdk/responses/info.py
skill_sdk/responses/reprompt.py
skill_sdk/responses/response.py
skill_sdk/responses/response_facets.py
skill_sdk/responses/task.py
skill_sdk/responses/touchpoint_instructions.py
skill_sdk/services/__init__.py
skill_sdk/services/base.py
skill_sdk/services/centraltoken.py
skill_sdk/services/location.py
skill_sdk/services/persistence.py
skill_sdk/services/text.py
skill_sdk/tools/__init__.py
skill_sdk/tools/translate.py
skill_sdk/ui/__init__.py
skill_sdk/ui/favicon.ico
skill_sdk/ui/index.html
skill_sdk/ui/css/app.d8642850.css
skill_sdk/ui/css/chunk-vendors.905e374c.css
skill_sdk/ui/js/app.2f455c99.js
skill_sdk/ui/js/app.2f455c99.js.map
skill_sdk-2.2.dist-info/LICENSE
skill_sdk-2.2.dist-info/METADATA
skill_sdk-2.2.dist-info/WHEEL
skill_sdk-2.2.dist-info/entry_points.txt
skill_sdk-2.2.dist-info/top_level.txt
skill_sdk-2.2.dist-info/RECORD
