Metadata-Version: 2.1
Name: skill-sdk
Version: 2.2
Summary: Magenta Voice Skill SDK for Python
Home-page: https://github.com/telekom/voice-skill-sdk/
Author: Deutsche Telekom Voicification Suite
Author-email: vineet.hingorani@telekom.de
License: MIT
Platform: UNKNOWN
Classifier: Development Status :: 3 - Alpha
Classifier: Intended Audience :: Developers
Classifier: Natural Language :: English
Classifier: License :: OSI Approved :: MIT License
Classifier: Programming Language :: Python
Classifier: Programming Language :: Python :: 3
Classifier: Programming Language :: Python :: 3.7
Classifier: Programming Language :: Python :: 3.8
Classifier: Programming Language :: Python :: 3.9
Classifier: Programming Language :: Python :: Implementation :: CPython
Requires-Python: >=3.7
Requires-Dist: PyJWT (~=2.6.0)
Requires-Dist: aiobreaker
Requires-Dist: babel (<2.12.0)
Requires-Dist: fastapi (<1,>=0.70.0)
Requires-Dist: httpx (<0.23.1,>=0.16)
Requires-Dist: isodate
Requires-Dist: nest-asyncio
Requires-Dist: orjson
Requires-Dist: pydantic (<2.0.0,>=1.8)
Requires-Dist: python-dateutil
Requires-Dist: pyyaml
Requires-Dist: starlette-context
Requires-Dist: uvicorn[standard]
Provides-Extra: all
Requires-Dist: starlette-exporter ; extra == 'all'
Requires-Dist: starlette-opentracing ; extra == 'all'
Provides-Extra: dev
Requires-Dist: black ; extra == 'dev'
Requires-Dist: gunicorn ; extra == 'dev'
Requires-Dist: jaeger-client ; extra == 'dev'
Requires-Dist: mypy (>=0.9) ; extra == 'dev'
Requires-Dist: pytest ; extra == 'dev'
Requires-Dist: pytest-asyncio ; extra == 'dev'
Requires-Dist: pytest-cov ; extra == 'dev'
Requires-Dist: pytest-mock ; extra == 'dev'
Requires-Dist: questionary ; extra == 'dev'
Requires-Dist: respx ; extra == 'dev'
Requires-Dist: starlette-exporter ; extra == 'dev'
Requires-Dist: starlette-opentracing ; extra == 'dev'
Requires-Dist: starlette[full] ; extra == 'dev'
Requires-Dist: types-PyYAML ; extra == 'dev'
Requires-Dist: types-orjson ; extra == 'dev'
Requires-Dist: types-pkg-resources ; extra == 'dev'
Requires-Dist: types-python-dateutil ; extra == 'dev'
